Metadata-Version: 2.1
Name: odoo8-addon-mrp-production-partner-note
Version: 8.0.1.0.0.99.dev20
Summary: MRP - Partner production notes
Home-page: http://www.odoomrp.com
Author: OdooMRP team,AvanzOSC,Serv. Tecnol. Avanzados - Pedro M. Baeza, Odoo Community Association (OCA)
Author-email: support@odoo-community.org
License: UNKNOWN
Platform: UNKNOWN
Classifier: Programming Language :: Python
Classifier: Framework :: Odoo
Requires-Python: ~=2.7
Requires-Dist: odoo8-addon-mrp-production-note
Requires-Dist: odoo (<9.0a,>=8.0a)
